<APPLANG>
	<PHOTOVIEW>
		<DISPLAYNAME>Photos</DISPLAYNAME>
		<DESCRIPTION>Display Name</DESCRIPTION>
		<THUMBSHEADER>THUMBS VIEW</THUMBSHEADER>
		<NOPATHSET>NO PATH SET IN SETTINGS</NOPATHSET>
        <MYPHOTOS>MY PHOTOS</MYPHOTOS>
        <ROTATE>ROTATE</ROTATE>
        <SETWALLPAPER>Set Wallpaper</SETWALLPAPER>
        <EMAILPHOTO>EMAIL PHOTO</EMAILPHOTO>
		<DELETECONFIRM>ARE YOU SURE YOU WANT TO REMOVE THIS PHOTO?</DELETECONFIRM>
		<EDIT>Delete</EDIT>
		<SLIDESHOW>Slideshow</SLIDESHOW>
		<VIEW>View</VIEW>
	</PHOTOVIEW>
	<SETUP>
		<HEADER>PHOTOVIEW</HEADER>
		<PHOTOPATH>DEFAULT PHOTO PATH</PHOTOPATH>
		<ENTERPHOTOPATH>ENTER DEFAULT PHOTO PATH</ENTERPHOTOPATH>
	</SETUP>
</APPLANG>